setup.py
cnorm/__init__.py
cnorm/__main__.py
cnorm/nodes.py
cnorm.egg-info/PKG-INFO
cnorm.egg-info/SOURCES.txt
cnorm.egg-info/dependency_links.txt
cnorm.egg-info/requires.txt
cnorm.egg-info/top_level.txt
cnorm/parsing/__init__.py
cnorm/parsing/declaration.py
cnorm/parsing/expression.py
cnorm/parsing/literal.py
cnorm/parsing/statement.py
cnorm/passes/__init__.py
cnorm/passes/pickle.py
cnorm/passes/to_c.py
cnorm/passes/visit.py