Metadata-Version: 1.1
Name: cnorm
Version: 4.0.5
Summary: CNORM a C Front-end in Python
Home-page: https://github.com/LionelAuroux/cnorm
Author: Lionel Auroux
Author-email: lionel.auroux@gmail.com
License: GPLv3
Keywords: parsing,grammar,C
Platform: UNKNOWN
Classifier: Development Status :: 5 - Production/Stable
Classifier: Intended Audience :: Developers
Classifier: License :: OSI Approved :: GNU General Public License v3 (GPLv3)
Classifier: Programming Language :: Python :: 3.3
Classifier: Topic :: Software Development :: Code Generators
Classifier: Topic :: Software Development :: Compilers
Classifier: Topic :: Software Development :: Libraries :: Python Modules
